AUTHORS
ChangeLog
LICENSE
README
setup.py
digested/__init__.py
digested/admin.py
digested/digest_managers.py
digested/models.py
digested/migrations/0001_initial.py
digested/migrations/__init__.py
dist/django-digested-0.1.2.tar.gz
django_digested.egg-info/PKG-INFO
django_digested.egg-info/SOURCES.txt
django_digested.egg-info/dependency_links.txt
django_digested.egg-info/not-zip-safe
django_digested.egg-info/top_level.txt