Metadata-Version: 1.0
Name: django-digested
Version: 0.1.2
Summary: Allows you to set up notification emails for your users, sent out either immediately or in regular batches
Home-page: http://unpublished.test
Author: Jerome Baum
Author-email: jerome@jeromebaum.com
License: See LICENSE file
Platform: UNKNOWN
